maxspeed/__init__.py
maxspeed/core.py
maxspeed-0.0.0.9.dist-info/METADATA
maxspeed-0.0.0.9.dist-info/WHEEL
maxspeed-0.0.0.9.dist-info/top_level.txt
maxspeed-0.0.0.9.dist-info/RECORD
