Metadata-Version: 2.4
Name: maxspeed
Version: 0.0.0.9
Requires-Dist: pyperclip
Dynamic: requires-dist
